{
  "data": {
    "496": {
      "id": 496,
      "name": "神域之门",
      "desc": "天之门、地之门、神之门的总称",
      "kind": 1,
      "link": [
        {
          "id": 493,
          "url": "https://api.seerapi.com/v1/glossary_entry/493"
        },
        {
          "id": 494,
          "url": "https://api.seerapi.com/v1/glossary_entry/494"
        },
        {
          "id": 495,
          "url": "https://api.seerapi.com/v1/glossary_entry/495"
        }
      ],
      "pet": [
        {
          "id": 4888,
          "url": "https://api.seerapi.com/v1/pet/4888"
        }
      ]
    }
  },
  "hash": "1fc957a6"
}