{
  "id": 423,
  "name": "杰出新兵套装",
  "transform": false,
  "tran_speed": 0.0,
  "suit_desc": "赛尔们在冒险中获得的套装，能够改变外观或者增强力量",
  "equips": [
    {
      "id": 1300926,
      "url": "https://api.seerapi.com/v1/equip/1300926"
    },
    {
      "id": 1300927,
      "url": "https://api.seerapi.com/v1/equip/1300927"
    },
    {
      "id": 1300928,
      "url": "https://api.seerapi.com/v1/equip/1300928"
    },
    {
      "id": 1300929,
      "url": "https://api.seerapi.com/v1/equip/1300929"
    },
    {
      "id": 1300930,
      "url": "https://api.seerapi.com/v1/equip/1300930"
    }
  ],
  "bonus": {
    "newse_id": 7759,
    "eid_effect": null,
    "id": 423,
    "desc": "背包内精灵全属性+55点，命中率+4%",
    "effective_pets": [],
    "attribute": {
      "atk": 55,
      "def": 55,
      "sp_atk": 55,
      "sp_def": 55,
      "spd": 55,
      "hp": 55,
      "percent": false,
      "total": 330
    }
  },
  "hash": "6a4e919b"
}