{
  "is_ability_bonus": false,
  "ability_desc": null,
  "type": {
    "id": 2,
    "url": "https://api.seerapi.com/v1/achievement_type/2"
  },
  "branch": {
    "id": 172,
    "url": "https://api.seerapi.com/v1/achievement_branch/172"
  },
  "next_level_achievement": null,
  "prev_level_achievement": null,
  "attr_bonus": null,
  "id": 3172004,
  "name": "群虫荣光",
  "point": 10,
  "desc": "通关S-艾莉安娜【地狱难度】关卡获得",
  "is_hide": false,
  "title_id": 568,
  "title": "群虫荣光",
  "original_title": "群虫荣光",
  "hash": "72c9357d"
}