{
  "id": 1367,
  "args_num": 2,
  "info": "随机附加{0}种异常状态，未触发则{1}回合内令对手使用的属性技能无效",
  "info_formatting_adjustment": "随机附加{0}种异常状态\r\n--><condition>未触发</condition>则{1}回合内令对手使用的属性技能无效",
  "pve_effective": false,
  "param": null,
  "skill": [
    {
      "id": 26302,
      "url": "https://api.seerapi.com/v1/skill/26302/"
    },
    {
      "id": 26938,
      "url": "https://api.seerapi.com/v1/skill/26938/"
    },
    {
      "id": 28351,
      "url": "https://api.seerapi.com/v1/skill/28351/"
    }
  ],
  "tag": [
    {
      "id": 813,
      "url": "https://api.seerapi.com/v1/skill_effect_type_tag/813/"
    },
    {
      "id": 44313,
      "url": "https://api.seerapi.com/v1/skill_effect_type_tag/44313/"
    }
  ],
  "hash": "ece919f"
}