{
  "id": 982,
  "args_num": 3,
  "info": "{0}%使对手{1}，自身每处于一种能力提升状态则概率提高{2}%",
  "info_formatting_adjustment": "{0}%使对手{1}\r\n--><condition>自身每处于一种能力强化状态</condition>则概率提高{2}%",
  "pve_effective": true,
  "param": [
    {
      "position": 1,
      "param": {
        "id": 1,
        "url": "https://api.seerapi.com/v1/skill_effect_param/1/"
      }
    }
  ],
  "skill": [
    {
      "id": 19733,
      "url": "https://api.seerapi.com/v1/skill/19733/"
    },
    {
      "id": 25581,
      "url": "https://api.seerapi.com/v1/skill/25581/"
    },
    {
      "id": 30872,
      "url": "https://api.seerapi.com/v1/skill/30872/"
    },
    {
      "id": 31956,
      "url": "https://api.seerapi.com/v1/skill/31956/"
    },
    {
      "id": 32232,
      "url": "https://api.seerapi.com/v1/skill/32232/"
    },
    {
      "id": 32917,
      "url": "https://api.seerapi.com/v1/skill/32917/"
    },
    {
      "id": 34506,
      "url": "https://api.seerapi.com/v1/skill/34506/"
    },
    {
      "id": 34516,
      "url": "https://api.seerapi.com/v1/skill/34516/"
    },
    {
      "id": 34855,
      "url": "https://api.seerapi.com/v1/skill/34855/"
    },
    {
      "id": 36402,
      "url": "https://api.seerapi.com/v1/skill/36402/"
    },
    {
      "id": 36453,
      "url": "https://api.seerapi.com/v1/skill/36453/"
    },
    {
      "id": 37734,
      "url": "https://api.seerapi.com/v1/skill/37734/"
    }
  ],
  "tag": [
    {
      "id": 813,
      "url": "https://api.seerapi.com/v1/skill_effect_type_tag/813/"
    }
  ],
  "hash": "a47bfc3a"
}