{
  "id": 739,
  "args_num": 1,
  "info": "当回合未击败对手则有{0}%将对手所有技能PP值降为0",
  "info_formatting_adjustment": null,
  "pve_effective": false,
  "param": null,
  "skill": [
    {
      "id": 17166,
      "url": "https://api.seerapi.com/v1/skill/17166"
    },
    {
      "id": 18124,
      "url": "https://api.seerapi.com/v1/skill/18124"
    },
    {
      "id": 19904,
      "url": "https://api.seerapi.com/v1/skill/19904"
    },
    {
      "id": 30605,
      "url": "https://api.seerapi.com/v1/skill/30605"
    },
    {
      "id": 34511,
      "url": "https://api.seerapi.com/v1/skill/34511"
    },
    {
      "id": 35006,
      "url": "https://api.seerapi.com/v1/skill/35006"
    },
    {
      "id": 35744,
      "url": "https://api.seerapi.com/v1/skill/35744"
    },
    {
      "id": 36805,
      "url": "https://api.seerapi.com/v1/skill/36805"
    }
  ],
  "tag": [
    {
      "id": 46440,
      "url": "https://api.seerapi.com/v1/skill_effect_type_tag/46440"
    }
  ],
  "hash": "6ae60de8"
}