{
  "id": 571,
  "args_num": 2,
  "info": "{0}回合后对对手造成{1}点固定伤害 重复使用无法叠加",
  "info_formatting_adjustment": null,
  "pve_effective": true,
  "param": null,
  "skill": [
    {
      "id": 16869,
      "url": "https://api.seerapi.com/v1/skill/16869"
    },
    {
      "id": 23050,
      "url": "https://api.seerapi.com/v1/skill/23050"
    },
    {
      "id": 23372,
      "url": "https://api.seerapi.com/v1/skill/23372"
    },
    {
      "id": 23499,
      "url": "https://api.seerapi.com/v1/skill/23499"
    },
    {
      "id": 23940,
      "url": "https://api.seerapi.com/v1/skill/23940"
    },
    {
      "id": 25940,
      "url": "https://api.seerapi.com/v1/skill/25940"
    },
    {
      "id": 26080,
      "url": "https://api.seerapi.com/v1/skill/26080"
    },
    {
      "id": 26178,
      "url": "https://api.seerapi.com/v1/skill/26178"
    },
    {
      "id": 26503,
      "url": "https://api.seerapi.com/v1/skill/26503"
    },
    {
      "id": 26758,
      "url": "https://api.seerapi.com/v1/skill/26758"
    },
    {
      "id": 26854,
      "url": "https://api.seerapi.com/v1/skill/26854"
    },
    {
      "id": 27293,
      "url": "https://api.seerapi.com/v1/skill/27293"
    },
    {
      "id": 27354,
      "url": "https://api.seerapi.com/v1/skill/27354"
    },
    {
      "id": 27359,
      "url": "https://api.seerapi.com/v1/skill/27359"
    },
    {
      "id": 27555,
      "url": "https://api.seerapi.com/v1/skill/27555"
    },
    {
      "id": 27669,
      "url": "https://api.seerapi.com/v1/skill/27669"
    },
    {
      "id": 27807,
      "url": "https://api.seerapi.com/v1/skill/27807"
    },
    {
      "id": 28498,
      "url": "https://api.seerapi.com/v1/skill/28498"
    },
    {
      "id": 28903,
      "url": "https://api.seerapi.com/v1/skill/28903"
    },
    {
      "id": 28912,
      "url": "https://api.seerapi.com/v1/skill/28912"
    },
    {
      "id": 29034,
      "url": "https://api.seerapi.com/v1/skill/29034"
    },
    {
      "id": 33365,
      "url": "https://api.seerapi.com/v1/skill/33365"
    },
    {
      "id": 34649,
      "url": "https://api.seerapi.com/v1/skill/34649"
    },
    {
      "id": 34875,
      "url": "https://api.seerapi.com/v1/skill/34875"
    },
    {
      "id": 34926,
      "url": "https://api.seerapi.com/v1/skill/34926"
    },
    {
      "id": 35795,
      "url": "https://api.seerapi.com/v1/skill/35795"
    },
    {
      "id": 36725,
      "url": "https://api.seerapi.com/v1/skill/36725"
    },
    {
      "id": 37130,
      "url": "https://api.seerapi.com/v1/skill/37130"
    },
    {
      "id": 37749,
      "url": "https://api.seerapi.com/v1/skill/37749"
    }
  ],
  "tag": [
    {
      "id": 60828,
      "url": "https://api.seerapi.com/v1/skill_effect_type_tag/60828"
    }
  ],
  "hash": "47c60a56"
}