{
  "count": 36,
  "next": null,
  "previous": null,
  "first": null,
  "last": null,
  "results": [
    {
      "id": 0,
      "name": "麻痹",
      "url": "https://api.seerapi.com/v1/battle_effect/0/"
    },
    {
      "id": 1,
      "name": "中毒",
      "url": "https://api.seerapi.com/v1/battle_effect/1/"
    },
    {
      "id": 2,
      "name": "烧伤",
      "url": "https://api.seerapi.com/v1/battle_effect/2/"
    },
    {
      "id": 3,
      "name": "寄生对手",
      "url": "https://api.seerapi.com/v1/battle_effect/3/"
    },
    {
      "id": 4,
      "name": "寄生",
      "url": "https://api.seerapi.com/v1/battle_effect/4/"
    },
    {
      "id": 5,
      "name": "冻伤",
      "url": "https://api.seerapi.com/v1/battle_effect/5/"
    },
    {
      "id": 6,
      "name": "害怕",
      "url": "https://api.seerapi.com/v1/battle_effect/6/"
    },
    {
      "id": 7,
      "name": "疲惫",
      "url": "https://api.seerapi.com/v1/battle_effect/7/"
    },
    {
      "id": 8,
      "name": "睡眠",
      "url": "https://api.seerapi.com/v1/battle_effect/8/"
    },
    {
      "id": 9,
      "name": "石化",
      "url": "https://api.seerapi.com/v1/battle_effect/9/"
    },
    {
      "id": 10,
      "name": "混乱",
      "url": "https://api.seerapi.com/v1/battle_effect/10/"
    },
    {
      "id": 11,
      "name": "衰弱",
      "url": "https://api.seerapi.com/v1/battle_effect/11/"
    },
    {
      "id": 12,
      "name": "山神守护",
      "url": "https://api.seerapi.com/v1/battle_effect/12/"
    },
    {
      "id": 13,
      "name": "易燃",
      "url": "https://api.seerapi.com/v1/battle_effect/13/"
    },
    {
      "id": 14,
      "name": "狂暴",
      "url": "https://api.seerapi.com/v1/battle_effect/14/"
    },
    {
      "id": 15,
      "name": "冰封",
      "url": "https://api.seerapi.com/v1/battle_effect/15/"
    },
    {
      "id": 16,
      "name": "流血",
      "url": "https://api.seerapi.com/v1/battle_effect/16/"
    },
    {
      "id": 19,
      "name": "瘫痪",
      "url": "https://api.seerapi.com/v1/battle_effect/19/"
    },
    {
      "id": 20,
      "name": "失明",
      "url": "https://api.seerapi.com/v1/battle_effect/20/"
    },
    {
      "id": 21,
      "name": "异常免疫",
      "url": "https://api.seerapi.com/v1/battle_effect/21/"
    },
    {
      "id": 22,
      "name": "焚烬",
      "url": "https://api.seerapi.com/v1/battle_effect/22/"
    },
    {
      "id": 23,
      "name": "诅咒",
      "url": "https://api.seerapi.com/v1/battle_effect/23/"
    },
    {
      "id": 24,
      "name": "烈焰诅咒",
      "url": "https://api.seerapi.com/v1/battle_effect/24/"
    },
    {
      "id": 25,
      "name": "致命诅咒",
      "url": "https://api.seerapi.com/v1/battle_effect/25/"
    },
    {
      "id": 26,
      "name": "虚弱诅咒",
      "url": "https://api.seerapi.com/v1/battle_effect/26/"
    },
    {
      "id": 27,
      "name": "感染",
      "url": "https://api.seerapi.com/v1/battle_effect/27/"
    },
    {
      "id": 28,
      "name": "束缚",
      "url": "https://api.seerapi.com/v1/battle_effect/28/"
    },
    {
      "id": 29,
      "name": "失神",
      "url": "https://api.seerapi.com/v1/battle_effect/29/"
    },
    {
      "id": 30,
      "name": "沉默",
      "url": "https://api.seerapi.com/v1/battle_effect/30/"
    },
    {
      "id": 31,
      "name": "臣服",
      "url": "https://api.seerapi.com/v1/battle_effect/31/"
    },
    {
      "id": 32,
      "name": "凝滞",
      "url": "https://api.seerapi.com/v1/battle_effect/32/"
    },
    {
      "id": 33,
      "name": "星赐",
      "url": "https://api.seerapi.com/v1/battle_effect/33/"
    },
    {
      "id": 34,
      "name": "星哲",
      "url": "https://api.seerapi.com/v1/battle_effect/34/"
    },
    {
      "id": 35,
      "name": "超频",
      "url": "https://api.seerapi.com/v1/battle_effect/35/"
    },
    {
      "id": 36,
      "name": "沸涌",
      "url": "https://api.seerapi.com/v1/battle_effect/36/"
    },
    {
      "id": 37,
      "name": "砥砺",
      "url": "https://api.seerapi.com/v1/battle_effect/37/"
    }
  ],
  "hash": "dad928f5"
}