{
  "id": 1046,
  "args_num": 1,
  "info": "若对手不处于异常状态则附加对手最大体力1/{0}的百分比伤害",
  "info_formatting_adjustment": null,
  "pve_effective": false,
  "param": null,
  "skill": [
    {
      "id": 19989,
      "url": "https://api.seerapi.com/v1/skill/19989"
    },
    {
      "id": 28159,
      "url": "https://api.seerapi.com/v1/skill/28159"
    },
    {
      "id": 28393,
      "url": "https://api.seerapi.com/v1/skill/28393"
    },
    {
      "id": 30579,
      "url": "https://api.seerapi.com/v1/skill/30579"
    },
    {
      "id": 30796,
      "url": "https://api.seerapi.com/v1/skill/30796"
    },
    {
      "id": 30873,
      "url": "https://api.seerapi.com/v1/skill/30873"
    },
    {
      "id": 31210,
      "url": "https://api.seerapi.com/v1/skill/31210"
    },
    {
      "id": 31460,
      "url": "https://api.seerapi.com/v1/skill/31460"
    },
    {
      "id": 31966,
      "url": "https://api.seerapi.com/v1/skill/31966"
    },
    {
      "id": 32069,
      "url": "https://api.seerapi.com/v1/skill/32069"
    },
    {
      "id": 33405,
      "url": "https://api.seerapi.com/v1/skill/33405"
    },
    {
      "id": 34332,
      "url": "https://api.seerapi.com/v1/skill/34332"
    },
    {
      "id": 35719,
      "url": "https://api.seerapi.com/v1/skill/35719"
    },
    {
      "id": 35978,
      "url": "https://api.seerapi.com/v1/skill/35978"
    },
    {
      "id": 36822,
      "url": "https://api.seerapi.com/v1/skill/36822"
    },
    {
      "id": 37301,
      "url": "https://api.seerapi.com/v1/skill/37301"
    },
    {
      "id": 37474,
      "url": "https://api.seerapi.com/v1/skill/37474"
    },
    {
      "id": 37968,
      "url": "https://api.seerapi.com/v1/skill/37968"
    },
    {
      "id": 38200,
      "url": "https://api.seerapi.com/v1/skill/38200"
    }
  ],
  "tag": [
    {
      "id": 60828,
      "url": "https://api.seerapi.com/v1/skill_effect_type_tag/60828"
    }
  ],
  "hash": "501d5d45"
}