{
  "id": 361,
  "content": "奇米奈从小就身体虚弱，经常生病，连最基本的饮食起居都无法独立完成，只是没日没夜地卧床休息…各路医生也都来拜访过，没有人能解释清楚病因，甚至还有道士断定她是被诅咒的孩子…\\n“姐姐，我是不是又给你添麻烦了…”奇米奈躺在床上露出脑袋试探性地问道。“怎么会，傻孩子，你就放心休息吧，一切都会好起来的…姐姐啊，会一直陪着你的。”奇莉奈默默收整齐手里的欠款，轻轻地合上门，打扫干净大门口的封条和涂鸦，戴上斗笠，继续去寻找能救治帮助妹妹的人…\\n某天，奇莉奈回到家，眼前突然变得富丽堂皇，桌上摆满了丰盛的晚宴，炉子里还传来阵阵暖意，妹妹穿着一身晚礼服缓缓从卧室走出，奇莉奈停顿了一下…这一切…怎么可能是真的…童话般的幻象逐渐消散，奇莉奈知道自己需要休息一下了，此时奇米奈正好起身，说道：“姐姐，我刚刚梦到了家里变得特别明亮整洁，还有一个装在墙里的篝火，还有好多好吃的，对了对了，我还穿了特别漂亮的小裙子…”奇莉奈注视着奇米奈的双眼，似乎有些不同了…那双眼睛，清澄了许多…\\n从那以后…奇米奈的身体逐渐好起来了…但更加令奇莉奈惊讶的是，她那份敏锐的感知力和念能力。\\n当艾希丝第一次见识到这份力量时，也吓了一跳。想要修炼成如此强大的念能力除了需要几十年如一日的磨砺，还需要一颗十分纯净的心灵，而恰恰这两点是互斥的…也许是因为没有经过后天的锻炼，奇米奈每次使用能力后，需要很长的睡眠时间来进行恢复。而艾希丝之所以会器重这对姐妹的能力，还因为姐妹俩的互相信任，她们都将自己依托给对方，她们都知道，这个世界上，只要有彼此，就足够了。",
  "pet": {
    "id": 4160,
    "url": "https://api.seerapi.com/v1/pet/4160/"
  },
  "book": {
    "id": 2,
    "url": "https://api.seerapi.com/v1/pet_archive_story_book/2/"
  },
  "hash": "6241e6e4"
}