{
  "data": {
    "30461": {
      "id": 30461,
      "name": "应龙沧海啸",
      "power": 160,
      "max_pp": 5,
      "accuracy": 95,
      "crit_rate": 6.25,
      "priority": 0,
      "must_hit": true,
      "atk_num": 1,
      "info": null,
      "category": {
        "id": 2,
        "url": "https://api.seerapi.com/v1/skill_category/2"
      },
      "type": {
        "id": 2,
        "url": "https://api.seerapi.com/v1/element_type_combination/2"
      },
      "learned_by_pet": [],
      "skill_effect": [
        {
          "info": "双倍反转自身能力下降状态，反转成功则获得200点护盾",
          "args": [
            200
          ],
          "effect": {
            "id": 1038,
            "url": "https://api.seerapi.com/v1/skill_effect_type/1038"
          }
        },
        {
          "info": "先出手时100%自身特攻等级+2",
          "args": [
            2,
            100,
            2
          ],
          "effect": {
            "id": 474,
            "url": "https://api.seerapi.com/v1/skill_effect_type/474"
          }
        },
        {
          "info": "后出手时，100%使自身速度提升1个等级",
          "args": [
            4,
            100,
            1
          ],
          "effect": {
            "id": 186,
            "url": "https://api.seerapi.com/v1/skill_effect_type/186"
          }
        }
      ],
      "friend_skill_effect": [],
      "hide_effect": null
    }
  },
  "hash": "f77a7a8e"
}