{
  "id": 223,
  "name": "萨菲罗战斗装",
  "transform": false,
  "tran_speed": 0.0,
  "suit_desc": "赛尔们在冒险中获得的套装，能够改变外观或者增强力量",
  "equips": [
    {
      "id": 1300050,
      "url": "https://api.seerapi.com/v1/equip/1300050/"
    },
    {
      "id": 1300051,
      "url": "https://api.seerapi.com/v1/equip/1300051/"
    },
    {
      "id": 1300052,
      "url": "https://api.seerapi.com/v1/equip/1300052/"
    },
    {
      "id": 1300053,
      "url": "https://api.seerapi.com/v1/equip/1300053/"
    }
  ],
  "bonus": null,
  "hash": "ddd6c1c7"
}