{
  "id": 72,
  "name": "利爪机甲",
  "transform": false,
  "tran_speed": 0.0,
  "suit_desc": "赛尔们在冒险中获得的套装，能够改变外观或者增强力量",
  "equips": [
    {
      "id": 100261,
      "url": "https://api.seerapi.com/v1/equip/100261"
    },
    {
      "id": 100262,
      "url": "https://api.seerapi.com/v1/equip/100262"
    },
    {
      "id": 100263,
      "url": "https://api.seerapi.com/v1/equip/100263"
    },
    {
      "id": 100264,
      "url": "https://api.seerapi.com/v1/equip/100264"
    },
    {
      "id": 100265,
      "url": "https://api.seerapi.com/v1/equip/100265"
    }
  ],
  "bonus": null,
  "hash": "1dd1b9b9"
}