{
  "data": {
    "1800084": {
      "next_level_gem": {
        "id": 1800085,
        "url": "https://api.seerapi.com/v1/gem/1800085"
      },
      "category": {
        "id": 9,
        "url": "https://api.seerapi.com/v1/gem_category/9"
      },
      "effect": [
        {
          "info": "额外附加12点固定伤害",
          "args": [
            12
          ],
          "effect": {
            "id": 29,
            "url": "https://api.seerapi.com/v1/skill_effect_type/29"
          }
        }
      ],
      "item": {
        "id": 1800084,
        "url": "https://api.seerapi.com/v1/item/1800084"
      },
      "id": 1800084,
      "name": "固定伤害12宝石Lv4",
      "level": 4,
      "generation_id": 1,
      "inlay_rate": 100.0,
      "equivalent_level1_count": 32,
      "fail_compensate_range": [
        4,
        4
      ],
      "upgrade_cost": null
    }
  },
  "hash": "8f1c92aa"
}