{
  "data": {
    "441": {
      "type": {
        "id": 5,
        "url": "https://api.seerapi.com/v1/achievement_type/5"
      },
      "branch": {
        "id": 152,
        "url": "https://api.seerapi.com/v1/achievement_branch/152"
      },
      "next_level_achievement": null,
      "prev_level_achievement": null,
      "attr_bonus": null,
      "is_ability_bonus": false,
      "ability_desc": null,
      "id": 441,
      "name": "千古一帝",
      "point": 10,
      "desc": "活动获得",
      "is_hide": false,
      "achievement_id": 1110,
      "achievement_name": "千古一帝",
      "original_name": "千古一帝"
    }
  },
  "hash": "fd68f15b"
}