{
  "id": 27984,
  "name": "万浊澄清",
  "power": 0,
  "max_pp": 10,
  "accuracy": 95,
  "crit_rate": null,
  "priority": 0,
  "must_hit": true,
  "info": "消除对手回合类效果；对手受到的伤害提升了",
  "category": {
    "id": 4,
    "url": "https://api.seerapi.com/v1/skill_category/4"
  },
  "type": {
    "id": 8,
    "url": "https://api.seerapi.com/v1/element_type_combination/8"
  },
  "learned_by_pet": [],
  "skill_effect": [
    {
      "info": "消除对手回合类效果，若消除成功则使对手下1次使用的属性技能失效",
      "args": [
        1
      ],
      "effect": {
        "id": 976,
        "url": "https://api.seerapi.com/v1/skill_effect_type/976"
      }
    },
    {
      "info": "下2回合造成的攻击伤害额外提升100%",
      "args": [
        2,
        100
      ],
      "effect": {
        "id": 693,
        "url": "https://api.seerapi.com/v1/skill_effect_type/693"
      }
    }
  ],
  "friend_skill_effect": [],
  "hide_effect": null,
  "hash": "cfe5c092"
}