{
  "id": 764,
  "args_num": 2,
  "info": "{0}回合内若对手使用攻击技能降低对手最大体力的1/{1}",
  "info_formatting_adjustment": null,
  "pve_effective": false,
  "param": null,
  "skill": [
    {
      "id": 24029,
      "url": "https://api.seerapi.com/v1/skill/24029"
    },
    {
      "id": 24265,
      "url": "https://api.seerapi.com/v1/skill/24265"
    },
    {
      "id": 24375,
      "url": "https://api.seerapi.com/v1/skill/24375"
    },
    {
      "id": 24927,
      "url": "https://api.seerapi.com/v1/skill/24927"
    },
    {
      "id": 25102,
      "url": "https://api.seerapi.com/v1/skill/25102"
    },
    {
      "id": 25273,
      "url": "https://api.seerapi.com/v1/skill/25273"
    },
    {
      "id": 25783,
      "url": "https://api.seerapi.com/v1/skill/25783"
    },
    {
      "id": 26136,
      "url": "https://api.seerapi.com/v1/skill/26136"
    },
    {
      "id": 26354,
      "url": "https://api.seerapi.com/v1/skill/26354"
    },
    {
      "id": 26853,
      "url": "https://api.seerapi.com/v1/skill/26853"
    },
    {
      "id": 26940,
      "url": "https://api.seerapi.com/v1/skill/26940"
    },
    {
      "id": 26980,
      "url": "https://api.seerapi.com/v1/skill/26980"
    },
    {
      "id": 27068,
      "url": "https://api.seerapi.com/v1/skill/27068"
    },
    {
      "id": 27156,
      "url": "https://api.seerapi.com/v1/skill/27156"
    },
    {
      "id": 27412,
      "url": "https://api.seerapi.com/v1/skill/27412"
    },
    {
      "id": 27506,
      "url": "https://api.seerapi.com/v1/skill/27506"
    },
    {
      "id": 27802,
      "url": "https://api.seerapi.com/v1/skill/27802"
    },
    {
      "id": 27898,
      "url": "https://api.seerapi.com/v1/skill/27898"
    },
    {
      "id": 27913,
      "url": "https://api.seerapi.com/v1/skill/27913"
    },
    {
      "id": 27938,
      "url": "https://api.seerapi.com/v1/skill/27938"
    },
    {
      "id": 28017,
      "url": "https://api.seerapi.com/v1/skill/28017"
    },
    {
      "id": 28108,
      "url": "https://api.seerapi.com/v1/skill/28108"
    },
    {
      "id": 28176,
      "url": "https://api.seerapi.com/v1/skill/28176"
    },
    {
      "id": 28507,
      "url": "https://api.seerapi.com/v1/skill/28507"
    },
    {
      "id": 36039,
      "url": "https://api.seerapi.com/v1/skill/36039"
    },
    {
      "id": 36926,
      "url": "https://api.seerapi.com/v1/skill/36926"
    }
  ],
  "tag": [
    {
      "id": 60828,
      "url": "https://api.seerapi.com/v1/skill_effect_type_tag/60828"
    }
  ],
  "hash": "1e94f8f5"
}