{
  "id": 630,
  "content": "又至清晨，林中的薄雾尚未褪去，繁盛灵兽王也即将脱离梦乡。睡眼朦胧间，繁盛灵兽王似乎看到有一株三叶灵草从天空缓缓飘落，可当他惊喜地睁大双眼，却发现那只是一片普通的树叶。\\n繁盛灵兽王整理过思绪，起身于林间开始漫步，他反复回忆着那株三叶灵草，忽然有一片云海从记忆深处翻涌升腾。那株三叶灵草只生长在繁盛灵兽王的家乡——云之仙境，繁盛灵兽王已经难以记起自己上一次回到云之仙境是在何时。他在宇宙中游历了太久，经历了太多事情，或许已是时候回一次家乡。\\n循着记忆中的方向，繁盛灵兽王到达了一座位于古老石城中央的神殿。繁盛灵兽王踏上石阶，迈入神殿大门。殿内是一片属于灵兽的世界，云之仙境就在这片世界之中。\\n云之仙境是繁盛灵兽王的故乡，也是他记忆中最美丽的地方：灵兽们无忧无虑地生活在那片天地之间，日子幸福美满。拥有飞行能力的灵兽在空中翱翔而过，传递着对生命的祝福；善于奔跑的灵兽在花海中疾驰，感受着万物的生长。\\n云之仙境——这一片由云与梦所勾织的乐土让繁盛灵兽王的内心感受到了前所未有的平静。他蹄下生花，尽情奔跑于这片久违的大地。在途经一株三叶灵草时，繁盛灵兽王停下了脚步，无数美好的记忆在他脑海中翻涌，繁盛灵兽王也终于返璞归真，领悟了所有灵兽都从未看到过的全新境界。他从此不再提及“繁盛灵兽王”的称号，众生只要唤他“始祖灵兽”就够了。",
  "pet": {
    "id": 4750,
    "url": "https://api.seerapi.com/v1/pet/4750"
  },
  "book": {
    "id": 1,
    "url": "https://api.seerapi.com/v1/pet_archive_story_book/1"
  },
  "hash": "180a0384"
}