{
  "id": 638,
  "content": "从前，赫尔卡星上有一个以熔炉作为身躯的机器人，名叫赫蒂洛斯。它有着无与伦比的创造力，十分善于发明各种事物，而它所制造出的各种新发明也给居民们带来了方便，大家都喜欢它，还给它取了一个外号，叫做“熔炉老者”。可不知道从什么时候开始，居民们发现赫蒂洛斯好像已经很久都没出门了，大家都好奇地去赫蒂洛斯的工厂附近想要打听这位发明天才的消息，但只能听到墙后传来不休的锤音。\\n突然有一天，赫蒂洛斯再次出现在了大家面前。它兴奋地邀请大家去自己的工厂参观自己的新发明。好奇的居民们纷纷前去查看，只见有一尊特别高大的机器人站在赫蒂洛斯的工厂中央。这个机器人内部的机械部件极为精密，而它的外壳却是用典雅的白色石头雕砌而成，远远一看，就仿佛一个白色巨人。人们都问赫蒂洛斯这个巨大的机械雕像是什么，赫蒂洛斯得意地笑了笑，可是并没有回答。它转过身子向着所有人宣布道：“这颗星球上最完美的人造物诞生了！”接下来的日子里，居民们都好奇地关注着白色巨人的一举一动。这个白色巨人所展现出的行为完全不像是个机械造物，反而像一个活生生的居民一样在街道上行走、与居民们玩耍，而赫蒂洛斯也将白色巨人当作自己的孩子。\\n赫蒂洛斯将自己的创造能力毫无保留地赋予了白色巨人，白色巨人也走上了自己的发明之路。赫蒂洛斯每天欣喜地看着白色巨人在工厂中不断尝试着制造各种事物，白色巨人困了就去旁边坐下休息，饿了就吃些废旧金属零件补充力量，赫蒂洛斯无微不至地照顾着它，就像在照顾一个小孩。可突然有一天，赫蒂洛斯又来看望睡熟的白色巨人时，竟然发现白色巨人的新造物上闪烁着阵阵凝聚在一起的极强闪电，这股闪电快速流动着，就好像即将拥有真正的生命，赫蒂洛斯在此时突然明白，这个白色巨人所展现出的创造力已经超越了自己！这个白色巨人即将制造出这个世界上最为伟大的创造物！\\n赫蒂洛斯的头脑陷入了混乱：如果白色巨人真的能创造出更伟大的造物，那创造了白色巨人的自己真的还算是这颗星球上最厉害的创造者吗？赫蒂洛斯尝试说服自己接受这一切，但赫蒂洛斯的内心已经在不知不觉间被嫉妒填满。“我一定要创造出更伟大的杰作！”赫蒂洛斯说着便关起门开始了自己的新发明。不休的锤声在工厂中响了又响，可突然间强烈的爆炸声从工厂中响起，赫蒂洛斯的工厂就这样被夷为了平地。\\n没有人知道，这个曾经创造出了最杰出发明的发明家最后在制造些什么。原本是赫蒂洛斯工厂的位置，只剩下了一个白色巨人，依然孜孜不倦地进行着自己的创造事业。",
  "pet": {
    "id": 4759,
    "url": "https://api.seerapi.com/v1/pet/4759/"
  },
  "book": {
    "id": 1,
    "url": "https://api.seerapi.com/v1/pet_archive_story_book/1/"
  },
  "hash": "1c78cf64"
}