{
  "id": 291,
  "content": "正如其他天选之子一般，赫里斯从童年开始便表现的与他人不同。当其他孩子还在埋怨长弓太重难以拾起时，他仿佛拿到了自己最喜欢的玩具，仔细的抚摩着弓臂那极富美感的弧线，手指在弓弦上游走仿佛拨动着音符，他第一次觉得如此充实。\\n四蹄踏过了处处山涧、目光扫过了片片河谷，莱赫星的每一处大地仿佛都成了赫里斯的修炼场。远处悬挂的苹果、潺潺水流中的小石头，甚至隐藏在草陇中正在狂奔的兔子，都逃不过他的箭矢！\\n他爱这种掌控箭矢的感觉，他爱这把极具威力的长弓，在每次使用后他都会擦的干干净净，再包上裹布轻轻抚摸，他觉得没有什么会比自己的弓箭更珍贵。\\n直到弓弦被手上的血液㓎污，他才发现守护莱赫星上的同胞们才是他的信念，看着眼前倒下的巨兽和远处蔑视自己的那个身影，他觉得自己再也做不了什么了……\\n还好，体内那颗种子被激活了，一点点荧光正在他的身上越闪越亮！那点点光芒仿佛象征着胜利的荣光，圣骑·赫里斯以圣箭之名势要守护这片大地！",
  "pet": {
    "id": 3938,
    "url": "https://api.seerapi.com/v1/pet/3938/"
  },
  "book": {
    "id": 1,
    "url": "https://api.seerapi.com/v1/pet_archive_story_book/1/"
  },
  "hash": "44717843"
}