{
  "id": 40,
  "name": "天蛇系列",
  "mintmark": [
    {
      "id": 41676,
      "url": "https://api.seerapi.com/v1/mintmark/41676/"
    },
    {
      "id": 41677,
      "url": "https://api.seerapi.com/v1/mintmark/41677/"
    },
    {
      "id": 41678,
      "url": "https://api.seerapi.com/v1/mintmark/41678/"
    },
    {
      "id": 41679,
      "url": "https://api.seerapi.com/v1/mintmark/41679/"
    },
    {
      "id": 41680,
      "url": "https://api.seerapi.com/v1/mintmark/41680/"
    },
    {
      "id": 41681,
      "url": "https://api.seerapi.com/v1/mintmark/41681/"
    },
    {
      "id": 41682,
      "url": "https://api.seerapi.com/v1/mintmark/41682/"
    }
  ],
  "hash": "f1cd30d3"
}