{
  "id": 258,
  "desc": "使用技能时，10%概率使自身速度提升1个等级",
  "desc_formatting_adjustment": null,
  "pve_effective": false,
  "intensified": false,
  "is_adv": false,
  "pet": [
    {
      "id": 2145,
      "url": "https://api.seerapi.com/v1/pet/2145"
    },
    {
      "id": 2146,
      "url": "https://api.seerapi.com/v1/pet/2146"
    }
  ],
  "effect": null,
  "effect_alias": null,
  "tag": [
    {
      "id": 12,
      "url": "https://api.seerapi.com/v1/soulmark_tag/12"
    }
  ],
  "intensified_to": null,
  "from": null,
  "hash": "18a839d5"
}