{
  "data": {
    "6122009": {
      "is_ability_bonus": false,
      "ability_desc": null,
      "type": {
        "id": 5,
        "url": "https://api.seerapi.com/v1/achievement_type/5"
      },
      "branch": {
        "id": 122,
        "url": "https://api.seerapi.com/v1/achievement_branch/122"
      },
      "next_level_achievement": null,
      "prev_level_achievement": null,
      "attr_bonus": null,
      "id": 6122009,
      "name": "赛尔战斗力",
      "point": 15,
      "desc": "赛尔战斗力",
      "is_hide": true,
      "title_id": null,
      "title": "赛尔战斗力",
      "original_title": "赛尔战斗力"
    }
  },
  "hash": "9ec48f9"
}