{
  "id": 21281,
  "name": "剧毒蝶粉",
  "power": 0,
  "max_pp": 20,
  "accuracy": 100,
  "crit_rate": null,
  "priority": 0,
  "must_hit": false,
  "atk_num": 1,
  "info": null,
  "category": {
    "id": 4,
    "url": "https://api.seerapi.com/v1/skill_category/4"
  },
  "type": {
    "id": 8,
    "url": "https://api.seerapi.com/v1/element_type_combination/8"
  },
  "learned_by_pet": [],
  "skill_effect": [
    {
      "info": "命中后100%令对方中毒",
      "args": [
        100
      ],
      "effect": {
        "id": 11,
        "url": "https://api.seerapi.com/v1/skill_effect_type/11"
      }
    }
  ],
  "friend_skill_effect": [],
  "hide_effect": null,
  "hash": "4d1bed47"
}