{
  "id": 22130,
  "name": "坚韧之心",
  "power": 0,
  "max_pp": 5,
  "accuracy": 100,
  "crit_rate": null,
  "priority": 0,
  "must_hit": true,
  "info": "特攻提升了许多，自身受到的伤害减少了",
  "category": {
    "id": 4,
    "url": "https://api.seerapi.com/v1/skill_category/4/"
  },
  "type": {
    "id": 8,
    "url": "https://api.seerapi.com/v1/element_type_combination/8/"
  },
  "learned_by_pet": [],
  "skill_effect": [
    {
      "info": "技能使用成功时，100%改变自身特攻等级+2",
      "args": [
        2,
        100,
        2
      ],
      "effect": {
        "id": 4,
        "url": "https://api.seerapi.com/v1/skill_effect_type/4/"
      }
    },
    {
      "info": "2回合内每回合所受的伤害减少150点",
      "args": [
        2,
        150
      ],
      "effect": {
        "id": 463,
        "url": "https://api.seerapi.com/v1/skill_effect_type/463/"
      }
    }
  ],
  "friend_skill_effect": [],
  "hide_effect": null,
  "hash": "2e19e284"
}