{
  "id": 272,
  "content": "百丈高山平地起，石破天惊万峰断。格莱奥丹，一个可以自由操控高峰巨岩的精灵。他洋溢着饱满的热情与深深的正直。他年轻的身体中，蕴含着可以移山填海的斗志。有人说，一对一的战斗，他似乎从未失败过。沉着的脸上，体现出他面对战斗永不退却的决心。在大概率会失败的战斗前面，弱小之人只会选择逃跑。但他不一样，他只会昂首挺胸，接受所有的挑战，捍卫自己作为一个勇者的尊严。\\n很多人对踩在脚下的岩石没有任何敬畏之心。在他们眼里，高高在上的天空才是值得向往的对象。而脚下的岩石，无非是处于最底层可以任意践踏的东西罢了。只有他走到新的地方，会低下头来，捡起地上几颗可爱的石头细细端详。他的同行者总是不能理解他为何对地上的石块情有独钟，“啊，无非是个灰蒙蒙的丑石头罢了”。\\n但是，随着他与土地岩石的接触越来越深，大地也越来越听从他的召唤，他走过的地方，岩石随着他的足迹成拱成环，积土成山。",
  "pet": {
    "id": 3867,
    "url": "https://api.seerapi.com/v1/pet/3867/"
  },
  "book": {
    "id": 1,
    "url": "https://api.seerapi.com/v1/pet_archive_story_book/1/"
  },
  "hash": "dea5b645"
}