{
  "id": 1293,
  "args_num": 2,
  "info": "免疫下{0}次对手的攻击，免疫成功则自身全属性+{1}",
  "info_formatting_adjustment": "免疫下{0}次受到的攻击\r\n--><condition>免疫成功</condition>则自身全属性+{1}",
  "pve_effective": true,
  "param": null,
  "skill": [
    {
      "id": 25908,
      "url": "https://api.seerapi.com/v1/skill/25908"
    },
    {
      "id": 29005,
      "url": "https://api.seerapi.com/v1/skill/29005"
    }
  ],
  "tag": [
    {
      "id": 44313,
      "url": "https://api.seerapi.com/v1/skill_effect_type_tag/44313"
    },
    {
      "id": 44951,
      "url": "https://api.seerapi.com/v1/skill_effect_type_tag/44951"
    }
  ],
  "hash": "17517568"
}