{
  "is_ability_bonus": false,
  "ability_desc": null,
  "type": {
    "id": 4,
    "url": "https://api.seerapi.com/v1/achievement_type/4"
  },
  "branch": {
    "id": 45,
    "url": "https://api.seerapi.com/v1/achievement_branch/45"
  },
  "next_level_achievement": {
    "id": 740,
    "url": "https://api.seerapi.com/v1/achievement/740"
  },
  "prev_level_achievement": {
    "id": 738,
    "url": "https://api.seerapi.com/v1/achievement/738"
  },
  "attr_bonus": null,
  "id": 739,
  "name": "小试身手（三）",
  "point": 10,
  "desc": "击败100名对手",
  "is_hide": false,
  "title_id": null,
  "title": null,
  "original_title": null,
  "hash": "e9bf49fe"
}