{
  "id": 858,
  "is_variant_pet": false,
  "is_dark_pet": false,
  "is_shine_pet": false,
  "is_rare_pet": false,
  "is_breeding_pet": false,
  "is_fusion_pet": false,
  "evolution_chain": [
    {
      "id": 1912,
      "url": "https://api.seerapi.com/v1/pet/1912"
    },
    {
      "id": 5382,
      "url": "https://api.seerapi.com/v1/pet/5382"
    },
    {
      "id": 5386,
      "url": "https://api.seerapi.com/v1/pet/5386"
    },
    {
      "id": 5390,
      "url": "https://api.seerapi.com/v1/pet/5390"
    },
    {
      "id": 5394,
      "url": "https://api.seerapi.com/v1/pet/5394"
    },
    {
      "id": 5398,
      "url": "https://api.seerapi.com/v1/pet/5398"
    },
    {
      "id": 5402,
      "url": "https://api.seerapi.com/v1/pet/5402"
    }
  ],
  "hash": "efc4eb1c"
}