{
  "id": 89,
  "name": "猛禽战机",
  "transform": true,
  "tran_speed": 5.5,
  "suit_desc": "赛尔们在冒险中获得的套装，能够改变外观或者增强力量",
  "equips": [
    {
      "id": 100785,
      "url": "https://api.seerapi.com/v1/equip/100785"
    },
    {
      "id": 100786,
      "url": "https://api.seerapi.com/v1/equip/100786"
    },
    {
      "id": 100787,
      "url": "https://api.seerapi.com/v1/equip/100787"
    },
    {
      "id": 100788,
      "url": "https://api.seerapi.com/v1/equip/100788"
    }
  ],
  "bonus": null,
  "hash": "93a062e6"
}