{
  "id": 15,
  "name": "日常巡逻次数",
  "point_total": 65,
  "is_series": true,
  "achievement": [
    {
      "id": 14,
      "url": "https://api.seerapi.com/v1/achievement/14"
    },
    {
      "id": 15,
      "url": "https://api.seerapi.com/v1/achievement/15"
    },
    {
      "id": 16,
      "url": "https://api.seerapi.com/v1/achievement/16"
    },
    {
      "id": 17,
      "url": "https://api.seerapi.com/v1/achievement/17"
    },
    {
      "id": 18,
      "url": "https://api.seerapi.com/v1/achievement/18"
    },
    {
      "id": 19,
      "url": "https://api.seerapi.com/v1/achievement/19"
    }
  ],
  "type": {
    "id": 0,
    "url": "https://api.seerapi.com/v1/achievement_type/0"
  },
  "hash": "b744a881"
}