{
  "id": 183,
  "args_num": 2,
  "info": "{0}回合内免疫并反弹{1}伤害",
  "info_formatting_adjustment": null,
  "pve_effective": true,
  "param": [
    {
      "position": 1,
      "param": {
        "id": 15,
        "url": "https://api.seerapi.com/v1/skill_effect_param/15"
      }
    }
  ],
  "skill": [
    {
      "id": 21563,
      "url": "https://api.seerapi.com/v1/skill/21563"
    },
    {
      "id": 21567,
      "url": "https://api.seerapi.com/v1/skill/21567"
    },
    {
      "id": 23755,
      "url": "https://api.seerapi.com/v1/skill/23755"
    }
  ],
  "tag": [
    {
      "id": 52161,
      "url": "https://api.seerapi.com/v1/skill_effect_type_tag/52161"
    },
    {
      "id": 51801,
      "url": "https://api.seerapi.com/v1/skill_effect_type_tag/51801"
    }
  ],
  "hash": "134c5a20"
}