{
  "id": 32479,
  "name": "万丈霞光",
  "power": 130,
  "max_pp": 10,
  "accuracy": 95,
  "crit_rate": 6.25,
  "priority": 0,
  "must_hit": false,
  "atk_num": 1,
  "info": null,
  "category": {
    "id": 2,
    "url": "https://api.seerapi.com/v1/skill_category/2"
  },
  "type": {
    "id": 64,
    "url": "https://api.seerapi.com/v1/element_type_combination/64"
  },
  "learned_by_pet": [],
  "skill_effect": [
    {
      "info": "本回合若没有打出致命一击则攻击",
      "args": [
        0,
        0,
        1,
        0,
        0,
        0
      ],
      "effect": {
        "id": 732,
        "url": "https://api.seerapi.com/v1/skill_effect_type/732"
      }
    }
  ],
  "friend_skill_effect": [],
  "hide_effect": null,
  "hash": "ecee38d7"
}