{
  "data": {
    "31426": {
      "id": 31426,
      "name": "幽冥夜刃",
      "power": 85,
      "max_pp": 20,
      "accuracy": 100,
      "crit_rate": 6.25,
      "priority": 3,
      "must_hit": false,
      "atk_num": 1,
      "info": null,
      "category": {
        "id": 1,
        "url": "https://api.seerapi.com/v1/skill_category/1"
      },
      "type": {
        "id": 50,
        "url": "https://api.seerapi.com/v1/element_type_combination/50"
      },
      "learned_by_pet": [],
      "skill_effect": [
        {
          "info": "消除对手回合类效果，消除成功则令对手随机2项技能PP值归零",
          "args": [
            2
          ],
          "effect": {
            "id": 1114,
            "url": "https://api.seerapi.com/v1/skill_effect_type/1114"
          }
        },
        {
          "info": "3回合内每回合70%闪避对手攻击",
          "args": [
            3,
            70
          ],
          "effect": {
            "id": 426,
            "url": "https://api.seerapi.com/v1/skill_effect_type/426"
          }
        }
      ],
      "friend_skill_effect": [],
      "hide_effect": null
    }
  },
  "hash": "5217324e"
}