{
  "id": 32935,
  "name": "救赎之光",
  "power": 130,
  "max_pp": 10,
  "accuracy": 95,
  "crit_rate": 0.0625,
  "priority": 0,
  "must_hit": true,
  "info": null,
  "category": {
    "id": 2,
    "url": "https://api.seerapi.com/v1/skill_category/2/"
  },
  "type": {
    "id": 52,
    "url": "https://api.seerapi.com/v1/element_type_combination/52/"
  },
  "learned_by_pet": [],
  "skill_effect": [
    {
      "info": "解除自身能力下降状态，若解除成功则3回合内免疫能力下降状态",
      "args": [
        3
      ],
      "effect": {
        "id": 710,
        "url": "https://api.seerapi.com/v1/skill_effect_type/710/"
      }
    }
  ],
  "friend_skill_effect": [],
  "hide_effect": null,
  "hash": "c3acceb7"
}