{
  "data": {
    "540": {
      "type": {
        "id": 2,
        "url": "https://api.seerapi.com/v1/achievement_type/2"
      },
      "branch": {
        "id": 170,
        "url": "https://api.seerapi.com/v1/achievement_branch/170"
      },
      "next_level_achievement": null,
      "prev_level_achievement": null,
      "attr_bonus": null,
      "is_ability_bonus": false,
      "ability_desc": null,
      "id": 540,
      "name": "完美观测者",
      "point": 10,
      "desc": "领取过任意一期叠加域“坍缩临界”全部三星奖励",
      "is_hide": false,
      "achievement_id": 546,
      "achievement_name": "完美观测者（三）",
      "original_name": "完美观测者"
    }
  },
  "hash": "bae1999f"
}