{
  "is_ability_bonus": false,
  "ability_desc": null,
  "type": {
    "id": 0,
    "url": "https://api.seerapi.com/v1/achievement_type/0"
  },
  "branch": {
    "id": 150,
    "url": "https://api.seerapi.com/v1/achievement_branch/150"
  },
  "next_level_achievement": null,
  "prev_level_achievement": {
    "id": 1150004,
    "url": "https://api.seerapi.com/v1/achievement/1150004"
  },
  "attr_bonus": null,
  "id": 1150005,
  "name": "基地拜访点赞（五）",
  "point": 30,
  "desc": "点赞300次好友基地",
  "is_hide": false,
  "title_id": 403,
  "title": "拜访达人",
  "original_title": "拜访达人",
  "hash": "3446b61d"
}