{
  "id": 1304,
  "args_num": 2,
  "info": "下{0}回合攻击忽略对手{1}%的双防值",
  "info_formatting_adjustment": null,
  "pve_effective": false,
  "param": null,
  "skill": [
    {
      "id": 25899,
      "url": "https://api.seerapi.com/v1/skill/25899"
    },
    {
      "id": 26143,
      "url": "https://api.seerapi.com/v1/skill/26143"
    },
    {
      "id": 26255,
      "url": "https://api.seerapi.com/v1/skill/26255"
    },
    {
      "id": 26336,
      "url": "https://api.seerapi.com/v1/skill/26336"
    },
    {
      "id": 26453,
      "url": "https://api.seerapi.com/v1/skill/26453"
    },
    {
      "id": 26489,
      "url": "https://api.seerapi.com/v1/skill/26489"
    },
    {
      "id": 26559,
      "url": "https://api.seerapi.com/v1/skill/26559"
    },
    {
      "id": 26578,
      "url": "https://api.seerapi.com/v1/skill/26578"
    },
    {
      "id": 26796,
      "url": "https://api.seerapi.com/v1/skill/26796"
    },
    {
      "id": 26830,
      "url": "https://api.seerapi.com/v1/skill/26830"
    },
    {
      "id": 27279,
      "url": "https://api.seerapi.com/v1/skill/27279"
    },
    {
      "id": 27296,
      "url": "https://api.seerapi.com/v1/skill/27296"
    },
    {
      "id": 27487,
      "url": "https://api.seerapi.com/v1/skill/27487"
    },
    {
      "id": 27528,
      "url": "https://api.seerapi.com/v1/skill/27528"
    },
    {
      "id": 27584,
      "url": "https://api.seerapi.com/v1/skill/27584"
    },
    {
      "id": 27672,
      "url": "https://api.seerapi.com/v1/skill/27672"
    },
    {
      "id": 27692,
      "url": "https://api.seerapi.com/v1/skill/27692"
    },
    {
      "id": 27745,
      "url": "https://api.seerapi.com/v1/skill/27745"
    },
    {
      "id": 27882,
      "url": "https://api.seerapi.com/v1/skill/27882"
    },
    {
      "id": 27942,
      "url": "https://api.seerapi.com/v1/skill/27942"
    },
    {
      "id": 28010,
      "url": "https://api.seerapi.com/v1/skill/28010"
    },
    {
      "id": 28272,
      "url": "https://api.seerapi.com/v1/skill/28272"
    },
    {
      "id": 28367,
      "url": "https://api.seerapi.com/v1/skill/28367"
    },
    {
      "id": 28423,
      "url": "https://api.seerapi.com/v1/skill/28423"
    },
    {
      "id": 28584,
      "url": "https://api.seerapi.com/v1/skill/28584"
    },
    {
      "id": 28738,
      "url": "https://api.seerapi.com/v1/skill/28738"
    },
    {
      "id": 28919,
      "url": "https://api.seerapi.com/v1/skill/28919"
    },
    {
      "id": 29048,
      "url": "https://api.seerapi.com/v1/skill/29048"
    },
    {
      "id": 36172,
      "url": "https://api.seerapi.com/v1/skill/36172"
    },
    {
      "id": 36678,
      "url": "https://api.seerapi.com/v1/skill/36678"
    },
    {
      "id": 36889,
      "url": "https://api.seerapi.com/v1/skill/36889"
    },
    {
      "id": 37484,
      "url": "https://api.seerapi.com/v1/skill/37484"
    },
    {
      "id": 38173,
      "url": "https://api.seerapi.com/v1/skill/38173"
    },
    {
      "id": 38189,
      "url": "https://api.seerapi.com/v1/skill/38189"
    }
  ],
  "tag": [
    {
      "id": 18673,
      "url": "https://api.seerapi.com/v1/skill_effect_type_tag/18673"
    }
  ],
  "hash": "a60f99c0"
}